djangoldp_polls/__init__.py
djangoldp_polls/apps.py
djangoldp_polls/djangoldp_urls.py
djangoldp_polls/factories.py
djangoldp_polls/filters.py
djangoldp_polls/permissions.py
djangoldp_polls/views.py
djangoldp_polls/management/__init__.py
djangoldp_polls/management/commands/__init__.py
djangoldp_polls/management/commands/mock_example.py
djangoldp_polls/migrations/0001_initial.py
djangoldp_polls/migrations/0002_auto_20220227_1910.py
djangoldp_polls/migrations/0003_auto_20220309_0809.py
djangoldp_polls/migrations/0004_question_required.py
djangoldp_polls/migrations/0005_auto_20220317_0715.py
djangoldp_polls/migrations/__init__.py
djangoldp_polls/models/__init__.py
djangoldp_polls/models/poll.py
djangoldp_polls/models/utils.py
djangoldp_polls/tests/__init__.py
djangoldp_polls/tests/default_test_case.py
djangoldp_polls/tests/runner.py
djangoldp_polls/tests/tests_models_question.py
djangoldp_polls-2.0.9.dist-info/METADATA
djangoldp_polls-2.0.9.dist-info/WHEEL
djangoldp_polls-2.0.9.dist-info/top_level.txt
djangoldp_polls-2.0.9.dist-info/RECORD
